qworder/__init__.py
qworder/cascading_rules.py
qworder/config.py
qworder/rules.py
qworder/word_generator.py
qworder-0.5.dist-info/LICENSE
qworder-0.5.dist-info/METADATA
qworder-0.5.dist-info/WHEEL
qworder-0.5.dist-info/top_level.txt
qworder-0.5.dist-info/RECORD
