Metadata-Version: 2.1
Name: qworder
Version: 0.5
Summary: QWorder simplifies strings representing sequences of quantum gates
Home-page: https://github.com/korsakjakub/qworder
Author: Jakub Korsak
Author-email: jakub.korsak@protonmail.com
License: gpl-3.0
Download-URL: https://github.com/korsakjakub/QWorder/archive/refs/tags/0.5.tar.gz
Keywords: QUANTUM,COMPUTING,GATESTRINGS,SIMPLIFIER,PAULI,MATRIX,HADAMARD
Platform: UNKNOWN
Classifier: Development Status :: 3 - Alpha
Classifier: Intended Audience :: Developers
Classifier: Topic :: Software Development :: Build Tools
Classifier: License :: OSI Approved :: GNU General Public License v3 (GPLv3)
Classifier: Programming Language :: Python :: 3
Classifier: Programming Language :: Python :: 3.7
Classifier: Programming Language :: Python :: 3.8
Classifier: Programming Language :: Python :: 3.9
License-File: LICENSE
Requires-Dist: numpy
